secret_code/__init__.py
secret_code/core.pyd
secret_code/index.py
secret_code/private_key.pem
secret_code/ui/__init__.py
secret_code/ui/c01.py
secret_code-0.1.0.dist-info/METADATA
secret_code-0.1.0.dist-info/WHEEL
secret_code-0.1.0.dist-info/top_level.txt
secret_code-0.1.0.dist-info/RECORD
