Metadata-Version: 2.1
Name: secret-code
Version: 0.1.0
Summary: ...
Home-page: 
Author: carson_jia
Author-email: 568166495@qq.com
License: MIT license
Classifier: Intended Audience :: Developers
Classifier: License :: OSI Approved :: MIT License
Classifier: Natural Language :: English
Classifier: Programming Language :: Python :: 3.8
Requires-Python: >=3.8
Requires-Dist: nicegui (>=1.4.0)
